datagrid_ai/__init__.py
datagrid_ai/_base_client.py
datagrid_ai/_client.py
datagrid_ai/_compat.py
datagrid_ai/_constants.py
datagrid_ai/_exceptions.py
datagrid_ai/_files.py
datagrid_ai/_models.py
datagrid_ai/_qs.py
datagrid_ai/_resource.py
datagrid_ai/_response.py
datagrid_ai/_streaming.py
datagrid_ai/_types.py
datagrid_ai/_version.py
datagrid_ai/pagination.py
datagrid_ai/py.typed
datagrid_ai/_utils/__init__.py
datagrid_ai/_utils/_compat.py
datagrid_ai/_utils/_datetime_parse.py
datagrid_ai/_utils/_logs.py
datagrid_ai/_utils/_proxy.py
datagrid_ai/_utils/_reflection.py
datagrid_ai/_utils/_resources_proxy.py
datagrid_ai/_utils/_streams.py
datagrid_ai/_utils/_sync.py
datagrid_ai/_utils/_transform.py
datagrid_ai/_utils/_typing.py
datagrid_ai/_utils/_utils.py
datagrid_ai/lib/.keep
datagrid_ai/lib/sse_converse/__init__.py
datagrid_ai/lib/sse_converse/converse_response_events.py
datagrid_ai/resources/__init__.py
datagrid_ai/resources/agents.py
datagrid_ai/resources/connections.py
datagrid_ai/resources/connectors.py
datagrid_ai/resources/files.py
datagrid_ai/resources/pages.py
datagrid_ai/resources/search.py
datagrid_ai/resources/secrets.py
datagrid_ai/resources/tools.py
datagrid_ai/resources/beta/__init__.py
datagrid_ai/resources/beta/beta.py
datagrid_ai/resources/beta/rewrite.py
datagrid_ai/resources/conversations/__init__.py
datagrid_ai/resources/conversations/conversations.py
datagrid_ai/resources/conversations/messages.py
datagrid_ai/resources/data_views/__init__.py
datagrid_ai/resources/data_views/data_views.py
datagrid_ai/resources/data_views/service_accounts.py
datagrid_ai/resources/knowledge/__init__.py
datagrid_ai/resources/knowledge/knowledge.py
datagrid_ai/resources/knowledge/tables/__init__.py
datagrid_ai/resources/knowledge/tables/records.py
datagrid_ai/resources/knowledge/tables/tables.py
datagrid_ai/resources/memory/__init__.py
datagrid_ai/resources/memory/memory.py
datagrid_ai/resources/memory/user.py
datagrid_ai/resources/organization/__init__.py
datagrid_ai-0.8.0.dist-info/METADATA
datagrid_ai-0.8.0.dist-info/WHEEL
datagrid_ai-0.8.0.dist-info/licenses/LICENSE
datagrid_ai-0.8.0.dist-info/RECORD
